questions_cli_app/cli.py
questions_cli_app/config.py
questions_cli_app/models.py
questions_cli_app/subject_settings.py
questions_cli_app/utils.py
questions_cli_app/core/__init__.py
questions_cli_app/core/classify.py
questions_cli_app/core/csv_io.py
questions_cli_app/core/generate.py
questions_cli_app/core/ingest.py
questions_cli_app/core/runner.py
questions_cli_app/core/subjects.py
questions_cli_app/services/llm.py
questions_cli_app/services/mongo.py
questions_cli-0.1.2.dist-info/METADATA
questions_cli-0.1.2.dist-info/WHEEL
questions_cli-0.1.2.dist-info/entry_points.txt
questions_cli-0.1.2.dist-info/top_level.txt
questions_cli-0.1.2.dist-info/RECORD
