Metadata-Version: 2.4
Name: questions-cli
Version: 0.1.2
Summary: CLI for processing search queries for the app
Author: InshaManowar
Keywords: cli,questions,search,queries
Classifier: Programming Language :: Python :: 3
Classifier: License :: OSI Approved :: MIT License
Classifier: Operating System :: OS Independent
Requires-Python: >=3.9
Requires-Dist: typer<1.0,>=0.9
Requires-Dist: pydantic>=2.4
Requires-Dist: pandas>=2.0
Requires-Dist: pymongo>=4.6
Requires-Dist: loguru>=0.7
Requires-Dist: orjson>=3.9
Requires-Dist: python-dotenv>=1.0
Requires-Dist: tqdm>=4.66
Requires-Dist: httpx>=0.27
Requires-Dist: tenacity>=8.2
Requires-Dist: pyyaml>=6.0
